README.md
setup.cfg
setup.py
snowclient/LICENSE.txt
snowclient/VERSION
snowclient/__init__.py
snowclient/api.py
snowclient/client.py
snowclient/errors.py
snowclient/querybuilder.py
snowclient/snowrecord.py
snowclient.egg-info/PKG-INFO
snowclient.egg-info/SOURCES.txt
snowclient.egg-info/dependency_links.txt
snowclient.egg-info/requires.txt
snowclient.egg-info/top_level.txt