Metadata-Version: 1.1
Name: snowclient
Version: 0.4.1
Summary: ServiceNow api client in python
Home-page: https://github.com/shaiguitar/snowclient.py
Author: shai rosenfeld
Author-email: shaiguitar@gmail.com
License: UNKNOWN
Download-URL: https://github.com/shaiguitar/snowclient.py
Platform: UNKNOWN
